README.txt
setup.py
django_wizard.egg-info/PKG-INFO
django_wizard.egg-info/SOURCES.txt
django_wizard.egg-info/dependency_links.txt
django_wizard.egg-info/not-zip-safe
django_wizard.egg-info/requires.txt
django_wizard.egg-info/top_level.txt
wizard/__init__.py
wizard/models.py
wizard/signals.py
wizard/test_urls.py
wizard/tests.py