Metadata-Version: 1.0
Name: django-wizard
Version: 0.2.0
Summary: A wizard that helps to control page flow.
Home-page: https://github.com/imtapps/django-wizard
Author: Matthew J. Morrison
Author-email: mattjmorrison@mattjmorrison.com
License: UNKNOWN
Platform: UNKNOWN
Classifier: Development Status :: 5 - Production/Stable
Classifier: Environment :: Web Environment
Classifier: Framework :: Django
Classifier: Intended Audience :: Developers
Classifier: License :: OSI Approved :: BSD License
Classifier: Operating System :: OS Independent
Classifier: Programming Language :: Python
Classifier: Topic :: Software Development
Classifier: Topic :: Software Development :: Libraries :: Application Frameworks
